README.md
setup.py
NeuralGraph/__init__.py
NeuralGraph/dataset.py
NeuralGraph/feature.py
NeuralGraph/layer.py
NeuralGraph/model.py
NeuralGraph/nfp.py
NeuralGraph/preprocessing.py
NeuralGraph/pretrained.py
NeuralGraph/util.py
torch_nfp.egg-info/PKG-INFO
torch_nfp.egg-info/SOURCES.txt
torch_nfp.egg-info/dependency_links.txt
torch_nfp.egg-info/requires.txt
torch_nfp.egg-info/top_level.txt